brats/__init__.py
brats/constants.py
brats/core/__init__.py
brats/core/brats_algorithm.py
brats/core/docker.py
brats/core/inpainting_algorithms.py
brats/core/missing_mri_algorithms.py
brats/core/segmentation_algorithms.py
brats/core/singularity.py
brats/data/meta/adult_glioma_pre_and_post_treatment.yml
brats/data/meta/adult_glioma_pre_treatment.yml
brats/data/meta/africa.yml
brats/data/meta/goat.yml
brats/data/meta/inpainting.yml
brats/data/meta/meningioma.yml
brats/data/meta/meningioma_rt.yml
brats/data/meta/metastases.yml
brats/data/meta/missing_mri.yml
brats/data/meta/pediatric.yml
brats/data/parameters/brats23_africa_sparkunn.yml
brats/data/parameters/brats23_inpainting_domaso.yml
brats/data/parameters/brats23_missing_mri_onembyte.yml
brats/data/parameters/brats24_adult_glioma_mist.yml
brats/data/parameters/brats24_inpainting_smint.yml
brats/data/parameters/brats24_missing_mri_cgv.yml
brats/data/parameters/dummy.yml
brats/preprocessing.py
brats/utils/__init__.py
brats/utils/algorithm_config.py
brats/utils/data_handling.py
brats/utils/exceptions.py
brats/utils/logging.py
brats/utils/zenodo.py
brats-0.1.6.dist-info/METADATA
brats-0.1.6.dist-info/WHEEL
brats-0.1.6.dist-info/licenses/LICENSE
brats-0.1.6.dist-info/RECORD
