Metadata-Version: 2.4
Name: brats
Version: 0.1.6
Summary: BraTS algorithms
License-Expression: Apache-2.0
License-File: LICENSE
Keywords: brain tumor,glioma,BraTS,brain lesion,segmentation,synthesis,inpainting
Author: Marcel Rosier
Author-email: marcel.rosier@tum.de
Requires-Python: >=3.8,<4.0
Classifier: Programming Language :: Python :: 3
Classifier: Programming Language :: Python :: 3.8
Classifier: Programming Language :: Python :: 3.9
Classifier: Programming Language :: Python :: 3.10
Classifier: Programming Language :: Python :: 3.11
Classifier: Programming Language :: Python :: 3.12
Classifier: Programming Language :: Python :: 3.13
Classifier: Programming Language :: Python :: 3.14
Provides-Extra: preprocessing
Requires-Dist: PyYAML (>=6.0.1)
Requires-Dist: brainles_preprocessing (>=0.6.7) ; (python_version >= "3.10") and (extra == "preprocessing")
Requires-Dist: dacite (>=1.8.0)
Requires-Dist: docker (>=7.0.0)
Requires-Dist: loguru (>=0.7.0)
Requires-Dist: nibabel (>=5.0.0)
Requires-Dist: numpy (>=1.21.0) ; python_version <= "3.9"
Requires-Dist: numpy (>=1.26.0) ; python_version >= "3.10"
Requires-Dist: rich (>=13.0.0)
Requires-Dist: spython (>=0.3.14)
